tool.py
xfdtest/__init__.py
xfdtest/xfdtest.py
xfdtest-1.0.3.dist-info/METADATA
xfdtest-1.0.3.dist-info/RECORD
xfdtest-1.0.3.dist-info/WHEEL
xfdtest-1.0.3.dist-info/top_level.txt
