Metadata-Version: 2.1
Name: xfdtest
Version: 1.0.3
Summary: niuB
Home-page: https://github.com
Author: xf
Author-email: 1271454083@qq.com
License: UNKNOWN
Platform: UNKNOWN
